rasp/__init__.py
rasp/assembler.py
rasp/cli.py
rasp/executable.py
rasp/instructions.py
rasp/machine.py
rasp/assembly/__init__.py
rasp/assembly/ast.py
rasp/assembly/parser.py
rasp/debug/__init__.py
rasp/debug/controller.py
rasp/debug/core.py
rasp/debug/view.py
tests/__init__.py
tests/acceptance.py
tests/fakes.py
tests/test_assembler.py
tests/test_executable.py
tests/test_machine.py
tests/test_profiler.py
tests/test_ui.py
RASP_Machine-0.1.2.dist-info/LICENSE
RASP_Machine-0.1.2.dist-info/METADATA
RASP_Machine-0.1.2.dist-info/WHEEL
RASP_Machine-0.1.2.dist-info/entry_points.txt
RASP_Machine-0.1.2.dist-info/top_level.txt
RASP_Machine-0.1.2.dist-info/RECORD
