Metadata-Version: 2.1
Name: RASP-Machine
Version: 0.1.2
Summary: Emulator for the RASP machines proposed by Cook & Reckow in 1973
Home-page: https://github.com/fchauvel/rasp-machine
Author: Franck Chauvel
Author-email: franck.chauvel@gmail.com
License: UNKNOWN
Project-URL: Documentation, https://fchauvel.github.io/rasp-machine
Project-URL: Bug Tracker, https://github.com/fchauvel/rasp-machine/issues
Platform: UNKNOWN
Classifier: Development Status :: 4 - Beta
Classifier: Environment :: Console
Classifier: Intended Audience :: Education
Classifier: License :: OSI Approved :: MIT License
Classifier: Natural Language :: English
Classifier: Operating System :: OS Independent
Classifier: Programming Language :: Python :: 3
Classifier: Topic :: Software Development :: Assemblers
Classifier: Topic :: System :: Emulators
Requires-Python: >=3.6
Requires-Dist: argparse (==1.4.0)
Requires-Dist: pyparsing (==2.4.7)
Provides-Extra: dev
Requires-Dist: build (==0.3.1) ; extra == 'dev'
Requires-Dist: twine (==3.4.1) ; extra == 'dev'
Requires-Dist: pytest (==6.2.4) ; extra == 'dev'
Requires-Dist: coverage (==5.5) ; extra == 'dev'
Requires-Dist: pyyaml (==5.4.1) ; extra == 'dev'
